harenpp/__init__.py
harenpp/haren.py
harenpp/utils.py
tests/__init__.py
tests/test_haren.py
harenpp-0.1.1.dist-info/LICENSE
harenpp-0.1.1.dist-info/METADATA
harenpp-0.1.1.dist-info/WHEEL
harenpp-0.1.1.dist-info/top_level.txt
harenpp-0.1.1.dist-info/RECORD
